d3dshot-stubs/METADATA.toml
d3dshot-stubs/__init__.pyi
d3dshot-stubs/capture_output.pyi
d3dshot-stubs/d3dshot.pyi
d3dshot-stubs/display.pyi
d3dshot-stubs/capture_outputs/__init__.pyi
d3dshot-stubs/capture_outputs/numpy_capture_output.pyi
d3dshot-stubs/capture_outputs/numpy_float_capture_output.pyi
d3dshot-stubs/capture_outputs/pil_capture_output.pyi
d3dshot-stubs/capture_outputs/pytorch_capture_output.pyi
d3dshot-stubs/capture_outputs/pytorch_float_capture_output.pyi
d3dshot-stubs/capture_outputs/pytorch_float_gpu_capture_output.pyi
d3dshot-stubs/capture_outputs/pytorch_gpu_capture_output.pyi
d3dshot-stubs/dll/__init__.pyi
d3dshot-stubs/dll/d3d.pyi
d3dshot-stubs/dll/dxgi.pyi
d3dshot-stubs/dll/shcore.pyi
d3dshot-stubs/dll/user32.pyi
types_D3DShot-0.1.0.5.dist-info/METADATA
types_D3DShot-0.1.0.5.dist-info/WHEEL
types_D3DShot-0.1.0.5.dist-info/top_level.txt
types_D3DShot-0.1.0.5.dist-info/RECORD
